mixsea/__init__.py
mixsea/helpers.py
mixsea/nsq.py
mixsea/overturn.py
mixsea/shearstrain.py
mixsea-0.2.0.dist-info/licenses/LICENSE
mixsea-0.2.0.dist-info/WHEEL
mixsea-0.2.0.dist-info/METADATA
mixsea-0.2.0.dist-info/RECORD
