Metadata-Version: 2.4
Name: mixsea
Version: 0.2.0
Summary: ocean mixing parameterizations
Author: mixsea developers
Author-email: mixsea developers <>
License-Expression: MIT
License-File: LICENSE
Classifier: Development Status :: 4 - Beta
Classifier: Intended Audience :: Science/Research
Classifier: Topic :: Scientific/Engineering :: Physics
Classifier: License :: OSI Approved :: MIT License
Classifier: Natural Language :: English
Classifier: Programming Language :: Python :: 3
Requires-Dist: numpy>=2
Requires-Dist: scipy>=1.6.0
Requires-Dist: gsw>=3.6
Requires-Python: >=3.9
Project-URL: Bug Tracker, https://github.com/modscripps/mixsea/issues
Project-URL: Changelog, https://github.com/modscripps/mixsea/blob/main/HISTORY.rst
Project-URL: Documentation, https://mixsea.readthedocs.io
Project-URL: Homepage, https://github.com/modscripps/mixsea
